{
  "about_text": "Chilena, mamá de un hijo hermoso y ya profesional. Periodista de las que aún escriben a mano. Tanto me gusta eso que tengo diarios de vida para escribir mis andanzas y mis pensamientos. Aprendiz de cocinera, más salado que dulce. Catadora de vinos por placer, me gusta probar nuevos vinos, nuevas variedades, viajar y conocer viñedos y bodegas. Comunicadora innata. Me gusta contar historias y escucharlas. Adicta a las redes sociales, y ahora a la inteligencia artificial.",
  "hero_intro": "De profesión periodista, me he especializado en el área de vino y gastronomía desde 1999. Comunicaciones, eventos, lanzamientos, ferias de vinos, contacto con la prensa, podcast.",
  "pull_quote": "Pendiente: cita en primera persona, 1–2 líneas. Lorem ipsum dolor sit amet, consectetur adipiscing elit sed do eiusmod.",
  "work_title": "Trabaja con María Paz Jiménez",
  "work_cards": [
    {
      "title": "Comunicación & Eventos",
      "desc": "Pendiente. 2–3 líneas. Lorem ipsum dolor sit amet, consectetur adipiscing elit. Sed do eiusmod tempor incididunt ut labore et dolore magna.",
      "images": [
        {
          "src": "/src/assets/comunicacion_eventos_1.jpg",
          "position": "center"
        },
        {
          "src": "/src/assets/comunicacion_eventos_2.jpeg",
          "position": "center"
        },
        {
          "src": "/src/assets/comunicacion_eventos_3.jpg",
          "position": "center"
        },
        {
          "src": "/src/assets/comunicacion_eventos_4.jpg",
          "position": "center"
        },
        {
          "src": "/src/assets/comunicacion_eventos_5.jpg",
          "position": "center"
        },
        {
          "src": "/src/assets/comunicacion_eventos_6.jpeg",
          "position": "center"
        }
      ]
    },
    {
      "title": "Catas & Maridajes",
      "desc": "Pendiente. 2–3 líneas. Lorem ipsum dolor sit amet, consectetur adipiscing elit. Sed do eiusmod tempor incididunt ut labore et dolore magna.",
      "images": [
        {
          "src": "/src/assets/catas_maridajes_1.jpg",
          "position": "center"
        },
        {
          "src": "/src/assets/catas_maridajes_2.jpg",
          "position": "center"
        },
        {
          "src": "/src/assets/catas_maridajes_3.jpg",
          "position": "center"
        },
        {
          "src": "/src/assets/catas_maridajes_4.jpg",
          "position": "center"
        },
        {
          "src": "/src/assets/catas_maridajes_5.jpg",
          "position": "center"
        },
        {
          "src": "/src/assets/catas_maridajes_6.jpg",
          "position": "center"
        },
        {
          "src": "/src/assets/catas_maridajes_7.jpg",
          "position": "center"
        },
        {
          "src": "/src/assets/catas_maridajes_8.jpeg",
          "position": "center"
        },
        {
          "src": "/src/assets/catas_maridajes_9.jpg",
          "position": "center"
        },
        {
          "src": "/src/assets/catas_maridajes_10.jpg",
          "position": "center"
        },
        {
          "src": "/src/assets/catas_maridajes_11.jpg",
          "position": "center"
        },
        {
          "src": "/src/assets/catas_maridajes_12.jpg",
          "position": "center"
        },
        {
          "src": "/src/assets/catas_maridajes_13.jpg",
          "position": "center"
        },
        {
          "src": "/src/assets/catas_maridajes_14.jpg",
          "position": "center"
        },
        {
          "src": "/src/assets/catas_maridajes_15.png",
          "position": "center"
        }
      ]
    },
    {
      "title": "Podcast Vinos con Marypepa",
      "desc": "Pendiente. 2–3 líneas. Lorem ipsum dolor sit amet, consectetur adipiscing elit. Sed do eiusmod tempor incididunt ut labore et dolore magna.",
      "images": [
        {
          "src": "/src/assets/podcast_1.jpg",
          "position": "center"
        },
        {
          "src": "/src/assets/podcast_2.jpg",
          "position": "center"
        },
        {
          "src": "/src/assets/podcast_3.jpg",
          "position": "center"
        },
        {
          "src": "/src/assets/podcast_4.jpg",
          "position": "center"
        },
        {
          "src": "/src/assets/podcast_5.jpg",
          "position": "center"
        },
        {
          "src": "/src/assets/podcast_6.jpg",
          "position": "center"
        },
        {
          "src": "/src/assets/podcast_7.jpg",
          "position": "center"
        },
        {
          "src": "/src/assets/podcast_8.jpg",
          "position": "center"
        },
        {
          "src": "/src/assets/podcast_9.png",
          "position": "center"
        },
        {
          "src": "/src/assets/podcast_10.png",
          "position": "center"
        },
        {
          "src": "/src/assets/podcast_11.webp",
          "position": "center"
        }
      ]
    }
  ],
  "podcast_desc": "Pendiente: 2–3 líneas. Lorem ipsum dolor sit amet, consectetur adipiscing elit. Sed do eiusmod tempor incididunt ut labore et dolore magna aliqua.",
  "contact_desc": "Pendiente. 1–2 líneas. Lorem ipsum dolor sit amet, consectetur adipiscing elit et dolore magna."
}